neuralartstudio/__init__.py
neuralartstudio/image_style.py
neuralartstudio/streamlit.py
neuralartstudio-0.1.0.dist-info/entry_points.txt
neuralartstudio-0.1.0.dist-info/LICENSE
neuralartstudio-0.1.0.dist-info/WHEEL
neuralartstudio-0.1.0.dist-info/METADATA
neuralartstudio-0.1.0.dist-info/RECORD
