Metadata-Version: 2.1
Name: neuralartstudio
Version: 0.1.0
Summary: App for experimenting and creating your own art using neural style transfer
Home-page: https://github.com/soumendra/neuralartstudio
License: MIT
Author: Soumendra Dhanee
Author-email: soumendra@gmail.com
Maintainer: Soumendra Dhanee
Maintainer-email: soumendra@gmail.com
Requires-Python: >=3.7,<4.0
Classifier: License :: OSI Approved :: MIT License
Classifier: Programming Language :: Python :: 3
Classifier: Programming Language :: Python :: 3.7
Classifier: Programming Language :: Python :: 3.8
Requires-Dist: matplotlib (>=3.2.1,<4.0.0)
Requires-Dist: numpy (>=1.18.5,<2.0.0)
Requires-Dist: pandas (>=1.0.4,<2.0.0)
Requires-Dist: plotly (>=4.8.1,<5.0.0)
Requires-Dist: streamlit (>=0.61.0,<0.62.0)
Requires-Dist: torch (>=1.5.0,<2.0.0)
Requires-Dist: torchvision (>=0.6.0,<0.7.0)
Project-URL: Documentation, https://github.com/soumendra/neuralartstudio
Project-URL: Repository, https://github.com/soumendra/neuralartstudio
